simpleprotocol/__init__.py
simpleprotocol/client.py
simpleprotocol/errors.py
simpleprotocol/server.py
simpleprotocol/tx.py
simple_protocol-0.1.13.dist-info/METADATA
simple_protocol-0.1.13.dist-info/WHEEL
simple_protocol-0.1.13.dist-info/top_level.txt
simple_protocol-0.1.13.dist-info/RECORD
